icebreaker/__init__.py
icebreaker/__main__.py
icebreaker/__version__.py
icebreaker/py.typed
icebreaker/version
icebreaker/_cli/__init__.py
icebreaker/_cli/_cli.py
icebreaker/_cli/commands/__init__.py
icebreaker/_cli/commands/fmt.py
icebreaker/_cli/commands/fmt_check.py
icebreaker/_cli/commands/version.py
icebreaker/_cli/interfaces/__init__.py
icebreaker/_cli/interfaces/_exit_code.py
icebreaker/_cli/interfaces/_printer.py
icebreaker/_cli/interfaces/_reader.py
icebreaker/_internal/__init__.py
icebreaker/_internal/formatting/__init__.py
icebreaker/_internal/formatting/_formatter.py
icebreaker/_internal/formatting/_ruff_formatter.py
icebreaker/_internal/typing/__init__.py
icebreaker/_internal/typing/_mypy_type_checker.py
icebreaker/_internal/typing/_type_checker.py
icebreaker/testing/__init__.py
icebreaker/testing/_test_code_formatting.py
icebreaker/testing/_test_code_typing.py
icebreaker/versioning/__init__.py
icebreaker/versioning/_version_file_based.py
arktika_icebreaker-0.6.0.dist-info/LICENSE
arktika_icebreaker-0.6.0.dist-info/METADATA
arktika_icebreaker-0.6.0.dist-info/WHEEL
arktika_icebreaker-0.6.0.dist-info/entry_points.txt
arktika_icebreaker-0.6.0.dist-info/top_level.txt
arktika_icebreaker-0.6.0.dist-info/RECORD
