Metadata-Version: 2.1
Name: arktika-icebreaker
Version: 0.6.0
Summary: Software Dev Kit
Author-email: Arktika <oss@arktika.io>
License: MIT License
Project-URL: Homepage, https://github.com/arktika-io/icebreaker
Project-URL: Source Code, https://github.com/arktika-io/icebreaker
Project-URL: Documentation, https://github.com/arktika-io/icebreaker/docs
Project-URL: Changelog, https://github.com/arktika-io/icebreaker/blob/main/CHANGELOG.md
Project-URL: Bug Tracker, https://github.com/arktika-io/icebreaker/issues
Requires-Python: >=3.12
License-File: LICENSE
Provides-Extra: cli
Requires-Dist: ruff ==0.* ; extra == 'cli'
Provides-Extra: dev
Requires-Dist: build ==1.* ; extra == 'dev'
Requires-Dist: twine ==4.* ; extra == 'dev'
Requires-Dist: hypothesis ==6.* ; extra == 'dev'
Requires-Dist: pytest ==7.* ; extra == 'dev'
Requires-Dist: pytest-asyncio ==0.* ; extra == 'dev'
Provides-Extra: testing
Requires-Dist: ruff ==0.* ; extra == 'testing'
Requires-Dist: mypy ==1.* ; extra == 'testing'
